{"cameraMode":{"drawMode":0,"name":"Shaded","section":"Shading Mode"},"sceneLighting":false,"audioPlay":false,"sceneViewState":{"m_AlwaysRefresh":false,"showFog":true,"showSkybox":false,"showFlares":true,"showImageEffects":true,"showParticleSystems":true,"showVisualEffectGraphs":true,"m_FxEnabled":true},"in2DMode":false,"pivot":{"x":27.0,"y":0.0,"z":27.0},"rotation":{"x":0.4284741282463074,"y":-0.005425408948212862,"z":0.0025703473947942259,"w":0.903541624546051},"size":38.18458557128906,"orthographic":false}